aliyunsdkcompanyreg/__init__.py
aliyunsdkcompanyreg/endpoint.py
aliyunsdkcompanyreg/request/__init__.py
aliyunsdkcompanyreg/request/v20200306/BindProduceAuthorizationRequest.py
aliyunsdkcompanyreg/request/v20200306/CloseIntentionForPartnerRequest.py
aliyunsdkcompanyreg/request/v20200306/CloseUserIntentionRequest.py
aliyunsdkcompanyreg/request/v20200306/CreateBusinessOpportunityRequest.py
aliyunsdkcompanyreg/request/v20200306/CreateProduceForPartnerRequest.py
aliyunsdkcompanyreg/request/v20200306/DescribePartnerConfigRequest.py
aliyunsdkcompanyreg/request/v20200306/GenerateUploadFilePolicyRequest.py
aliyunsdkcompanyreg/request/v20200306/GetAlipayUrlRequest.py
aliyunsdkcompanyreg/request/v20200306/ListIntentionNoteRequest.py
aliyunsdkcompanyreg/request/v20200306/ListProduceAuthorizationRequest.py
aliyunsdkcompanyreg/request/v20200306/ListUserDetailSolutionsRequest.py
aliyunsdkcompanyreg/request/v20200306/ListUserIntentionNotesRequest.py
aliyunsdkcompanyreg/request/v20200306/ListUserIntentionsRequest.py
aliyunsdkcompanyreg/request/v20200306/ListUserProduceOperateLogsRequest.py
aliyunsdkcompanyreg/request/v20200306/ListUserSolutionsRequest.py
aliyunsdkcompanyreg/request/v20200306/OperateProduceForPartnerRequest.py
aliyunsdkcompanyreg/request/v20200306/PutMeasureDataRequest.py
aliyunsdkcompanyreg/request/v20200306/PutMeasureReadyFlagRequest.py
aliyunsdkcompanyreg/request/v20200306/QueryAvailableNumbersRequest.py
aliyunsdkcompanyreg/request/v20200306/QueryBagRemainingRequest.py
aliyunsdkcompanyreg/request/v20200306/QueryCommodityConfigRequest.py
aliyunsdkcompanyreg/request/v20200306/QueryInstanceRequest.py
aliyunsdkcompanyreg/request/v20200306/QueryPartnerIntentionListRequest.py
aliyunsdkcompanyreg/request/v20200306/QueryPartnerProduceListRequest.py
aliyunsdkcompanyreg/request/v20200306/QueryUserNeedAuthRequest.py
aliyunsdkcompanyreg/request/v20200306/RejectSolutionRequest.py
aliyunsdkcompanyreg/request/v20200306/RejectUserSolutionRequest.py
aliyun_python_sdk_companyreg-2.2.5.dist-info/LICENSE
aliyun_python_sdk_companyreg-2.2.5.dist-info/METADATA
aliyun_python_sdk_companyreg-2.2.5.dist-info/WHEEL
aliyun_python_sdk_companyreg-2.2.5.dist-info/top_level.txt
aliyun_python_sdk_companyreg-2.2.5.dist-info/RECORD
